nonebot_plugin_palworld/__init__.py
nonebot_plugin_palworld/api.py
nonebot_plugin_palworld/config.py
nonebot_plugin_palworld/image.py
nonebot_plugin_palworld-0.1.11.dist-info/LICENSE
nonebot_plugin_palworld-0.1.11.dist-info/METADATA
nonebot_plugin_palworld-0.1.11.dist-info/WHEEL
nonebot_plugin_palworld-0.1.11.dist-info/top_level.txt
nonebot_plugin_palworld-0.1.11.dist-info/RECORD
