Metadata-Version: 2.1
Name: nonebot_plugin_palworld
Version: 0.1.11
Summary: 幻兽帕鲁服务器rest api使用
Home-page: https://github.com/huanxin996/nonebot_plugin_palworld
Author: Huan Xin
Author-email: mc.xiaolang@foxmail.com
Classifier: Programming Language :: Python :: 3
Classifier: License :: OSI Approved :: MIT License
Classifier: Operating System :: OS Independent
License-File: LICENSE
Requires-Dist: aiohttp>=3.11.11
Requires-Dist: nonebot2>=2.4.1
Requires-Dist: nonebot-adapter-onebot>=2.4.6
Requires-Dist: pillow>=9.5.0
Requires-Dist: nonebot-plugin-alconna>=0.54.0
